{
    "float_acc": "99.61%",
    "qat_acc": "99.43%",
    "akida_acc": "99.43%",
    "sparsity": "54.58%",
    "params": "1,156,054",
    "minimal_cycles": "36418493",
    "minimal_latency_ms": "91.046",
    "minimal_total_P": "154.7",
    "minimal_total_E": "14.839",
    "minimal_dyn_P": "41.2",
    "minimal_dyn_E": "3.948",
    "allnps_cycles": "18314559",
    "allnps_latency_ms": "45.786",
    "allnps_total_P": "196.2",
    "allnps_total_E": "9.389",
    "allnps_dyn_P": "81.2",
    "allnps_dyn_E": "3.887",
    "minimal_nps": "34",
    "minimal_passes": "2",
    "allnps_nps": "59",
    "allnps_passes": "2"
}
